cmd_parser/__about__.py
cmd_parser/__init__.py
cmd_parser/core.py
cmd_parser-0.0.1.dist-info/METADATA
cmd_parser-0.0.1.dist-info/WHEEL
cmd_parser-0.0.1.dist-info/licenses/LICENSE.txt
cmd_parser-0.0.1.dist-info/RECORD
